cr_bayesian_optim-0.1.1.dist-info/METADATA
cr_bayesian_optim-0.1.1.dist-info/WHEEL
cr_bayesian_optim-0.1.1.dist-info/entry_points.txt
cr_bayesian_optim-0.1.1.dist-info/licenses/LICENSE
cr_bayesian_optim/sim_branching.py
cr_bayesian_optim/plotting.py
cr_bayesian_optim/optimization.py
cr_bayesian_optim/__init__.py
cr_bayesian_optim/fractal_dim.py
cr_bayesian_optim/cr_bayesian_optim.pyi
cr_bayesian_optim/cr_bayesian_optim.cpython-312-darwin.so
cr_bayesian_optim-0.1.1.dist-info/RECORD
