Metadata-Version: 2.4
Name: cr_bayesian_optim
Version: 0.1.1
Classifier: Programming Language :: Rust
Classifier: Programming Language :: Python :: Implementation :: CPython
Classifier: Programming Language :: Python :: Implementation :: PyPy
Requires-Dist: numpy
Requires-Dist: matplotlib
Requires-Dist: tqdm
Requires-Dist: scipy
License-File: LICENSE
Requires-Python: >=3.8
